{"child_modules": [], "data_mtime": 1582706669, "dep_lines": [5, 1, 1, 1, 1, 1, 2, 3], "dep_prios": [10, 5, 30, 30, 20, 10, 10, 10], "dependencies": ["config", "builtins", "abc", "typing"], "deps_mtime": null, "hash": "824523ee9b7eca8d9eafcdbd183aa8a9", "id": "integrand_functions", "ignore_all": false, "interface_hash": "2bd275173dcabaa117e2405763e922c2", "mtime": 1583168049, "options": {"always_false": [], "always_true": [], "bazel": false, "check_untyped_defs": false, "disallow_any_decorated": false, "disallow_any_explicit": false, "disallow_any_expr": false, "disallow_any_generics": false, "disallow_any_unimported": false, "disallow_subclassing_any": false, "disallow_untyped_calls": false, "disallow_untyped_decorators": false, "disallow_untyped_defs": false, "follow_imports": "silent", "follow_imports_for_stubs": false, "ignore_errors": false, "ignore_missing_imports": true, "local_partial_types": false, "no_implicit_optional": false, "platform": "darwin", "quick_and_dirty": false, "show_none_errors": true, "strict_boolean": false, "strict_optional": true, "strict_optional_whitelist": null, "warn_no_return": true, "warn_return_any": false, "warn_unused_ignores": false}, "path": "/Users/eirikenger/OneDrive - UiT Office 365/Skole/5/10_semester/master/code/code-for-master/integrand_functions.py", "size": 3206, "suppressed": ["scipy", "scipy.constants", "scipy.special", "numpy"], "version_id": "0.620"}
